pyMolNetEnhancer/__init__.py
pyMolNetEnhancer/molnetenhancer.py
pyMolNetEnhancer-0.2.0.dist-info/LICENSE
pyMolNetEnhancer-0.2.0.dist-info/METADATA
pyMolNetEnhancer-0.2.0.dist-info/WHEEL
pyMolNetEnhancer-0.2.0.dist-info/top_level.txt
pyMolNetEnhancer-0.2.0.dist-info/RECORD
