Metadata-Version: 2.1
Name: pyMolNetEnhancer
Version: 0.2.0
Summary: A python implementation of MolNetEnhancer
Home-page: https://github.com/madeleineernst/pyMolNetEnhancer
Author: Madeleine Ernst, Ming Wang, Ricardo Silva
Author-email: mernst@ucsd.edu
License: UNKNOWN
Platform: UNKNOWN
Classifier: Programming Language :: Python :: 3
Classifier: License :: OSI Approved :: MIT License
Classifier: Operating System :: OS Independent
